sp_api_clients/__init__.py
sp_api_clients/authorization.py
sp_api_clients/base.py
sp_api_clients/cache.py
sp_api_clients/catalog_items.py
sp_api_clients/fba_inbound_eligibility.py
sp_api_clients/fba_inventory.py
sp_api_clients/fba_small_and_light.py
sp_api_clients/feeds.py
sp_api_clients/finances.py
sp_api_clients/fulfillment_inbound.py
sp_api_clients/fulfillment_outbound.py
sp_api_clients/merchant_fulfillment.py
sp_api_clients/messaging.py
sp_api_clients/notifications.py
sp_api_clients/orders.py
sp_api_clients/product_fees.py
sp_api_clients/product_pricing.py
sp_api_clients/reports.py
sp_api_clients/sales.py
sp_api_clients/sellers.py
sp_api_clients/services.py
sp_api_clients/shipping.py
sp_api_clients/solicitations.py
sp_api_clients/uploads.py
sp_api_clients-0.2.5.dist-info/METADATA
sp_api_clients-0.2.5.dist-info/WHEEL
sp_api_clients-0.2.5.dist-info/top_level.txt
sp_api_clients-0.2.5.dist-info/RECORD
