Metadata-Version: 2.1
Name: sp-api-clients
Version: 0.2.5
Summary: Amazon selling partner api clients.
Home-page: https://github.com/panhaoyu/sp-api-clients
Author: Haoyu Pan
Author-email: panhaoyu.china@outlook.com
License: UNKNOWN
Platform: UNKNOWN
Classifier: Programming Language :: Python :: 3
Classifier: License :: OSI Approved :: MIT License
Classifier: Operating System :: OS Independent
Requires-Python: >=3.5
Requires-Dist: peewee
Requires-Dist: cachetools
Requires-Dist: requests
Requires-Dist: boto3
